thalaivar/__init__.py
atwoone-1.0.2.dist-info/METADATA
atwoone-1.0.2.dist-info/WHEEL
atwoone-1.0.2.dist-info/top_level.txt
atwoone-1.0.2.dist-info/RECORD
