Metadata-Version: 2.4
Name: atwoone
Version: 1.0.2
Summary: Thalaivar's personal metadata module
Home-page: https://github.com/thalaivar96/
Author: Thalaivar
Author-email: t96halaivar@gmail.com
Classifier: Programming Language :: Python :: 3
Classifier: Operating System :: OS Independent
Requires-Python: >=3
Dynamic: author
Dynamic: author-email
Dynamic: classifier
Dynamic: description
Dynamic: description-content-type
Dynamic: home-page
Dynamic: requires-python
Dynamic: summary
